{
  "kind": "ref",
  "body_type": "[]sdk.Log",
  "body": [
    {
      "timestamp": "2025-10-01T10:13:37.823903-04:00",
      "message": "a ocuroot",
      "attributes": {
        "col": "30",
        "filename": "sdk/0.3.0/host.star",
        "line": "45",
        "thread": "build"
      },
      "stream": 0
    },
    {
      "timestamp": "2025-10-01T10:13:38.758817-04:00",
      "message": "",
      "attributes": {
        "col": "30",
        "filename": "sdk/0.3.0/host.star",
        "line": "45",
        "thread": "build"
      },
      "stream": 0
    }
  ]
}