{
  "kind": "ref",
  "body_type": "models.Task",
  "links": [
    "github.com/ocuroot/ocuroot/-/release.ocu.star/@/task/build_darwin_amd64"
  ],
  "body": {
    "run_ref": "github.com/ocuroot/ocuroot/-/release.ocu.star/@r11/task/build_darwin_amd64/1",
    "type": "task",
    "release": "github.com/ocuroot/ocuroot/-/release.ocu.star/@r11",
    "input": {
      "arch": {
        "value": "amd64"
      },
      "os": {
        "value": "darwin"
      },
      "version": {
        "ref": "github.com/ocuroot/ocuroot/-/release.ocu.star/@r11/task/increment_version#output/prerelease",
        "value": "0.3.14-4"
      }
    },
    "output": {}
  }
}