{
  "kind": "ref",
  "body_type": "[]sdk.Log",
  "body": [
    {
      "timestamp": "2025-10-01T13:35:51.487504-04:00",
      "message": "Building arm64 package for version: 0.3.16",
      "attributes": {
        "col": "30",
        "filename": "sdk/0.3.0/host.star",
        "line": "45",
        "thread": "build"
      },
      "stream": 0
    },
    {
      "timestamp": "2025-10-01T13:35:51.489546-04:00",
      "message": "Building arm64 package...",
      "attributes": {
        "col": "30",
        "filename": "sdk/0.3.0/host.star",
        "line": "45",
        "thread": "build"
      },
      "stream": 0
    },
    {
      "timestamp": "2025-10-01T13:35:51.501226-04:00",
      "message": "using deb packager...",
      "attributes": {
        "col": "30",
        "filename": "sdk/0.3.0/host.star",
        "line": "45",
        "thread": "build"
      },
      "stream": 0
    },
    {
      "timestamp": "2025-10-01T13:35:52.088926-04:00",
      "message": "created package: ../.build/packages/ocuroot_0.3.16_arm64.deb",
      "attributes": {
        "col": "30",
        "filename": "sdk/0.3.0/host.star",
        "line": "45",
        "thread": "build"
      },
      "stream": 0
    },
    {
      "timestamp": "2025-10-01T13:35:52.097211-04:00",
      "message": "using rpm packager...",
      "attributes": {
        "col": "30",
        "filename": "sdk/0.3.0/host.star",
        "line": "45",
        "thread": "build"
      },
      "stream": 0
    },
    {
      "timestamp": "2025-10-01T13:35:52.1544-04:00",
      "message": "created package: ../.build/packages/ocuroot_0.3.16_arm64.rpm",
      "attributes": {
        "col": "30",
        "filename": "sdk/0.3.0/host.star",
        "line": "45",
        "thread": "build"
      },
      "stream": 0
    },
    {
      "timestamp": "2025-10-01T13:35:52.159218-04:00",
      "message": "Package build complete!",
      "attributes": {
        "col": "30",
        "filename": "sdk/0.3.0/host.star",
        "line": "45",
        "thread": "build"
      },
      "stream": 0
    },
    {
      "timestamp": "2025-10-01T13:35:52.159334-04:00",
      "message": "Packages created:",
      "attributes": {
        "col": "30",
        "filename": "sdk/0.3.0/host.star",
        "line": "45",
        "thread": "build"
      },
      "stream": 0
    },
    {
      "timestamp": "2025-10-01T13:35:52.160637-04:00",
      "message": "  - /Users/tom/src/github.com/ocuroot/ocuroot/.build/packages/ocuroot_0.3.16_arm64.deb",
      "attributes": {
        "col": "30",
        "filename": "sdk/0.3.0/host.star",
        "line": "45",
        "thread": "build"
      },
      "stream": 0
    },
    {
      "timestamp": "2025-10-01T13:35:52.161906-04:00",
      "message": "  - /Users/tom/src/github.com/ocuroot/ocuroot/.build/packages/ocuroot_0.3.16_arm64.rpm",
      "attributes": {
        "col": "30",
        "filename": "sdk/0.3.0/host.star",
        "line": "45",
        "thread": "build"
      },
      "stream": 0
    },
    {
      "timestamp": "2025-10-01T13:35:52.175647-04:00",
      "message": "Testing ocuroot arm64 package for version: 0.3.16",
      "attributes": {
        "col": "30",
        "filename": "sdk/0.3.0/host.star",
        "line": "45",
        "thread": "build"
      },
      "stream": 0
    },
    {
      "timestamp": "2025-10-01T13:35:52.175859-04:00",
      "message": "✓ Found arm64 package",
      "attributes": {
        "col": "30",
        "filename": "sdk/0.3.0/host.star",
        "line": "45",
        "thread": "build"
      },
      "stream": 0
    },
    {
      "timestamp": "2025-10-01T13:35:52.179015-04:00",
      "message": "=== Testing ARM64 Package ===",
      "attributes": {
        "col": "30",
        "filename": "sdk/0.3.0/host.star",
        "line": "45",
        "thread": "build"
      },
      "stream": 0
    },
    {
      "timestamp": "2025-10-01T13:35:52.436593-04:00",
      "message": "#1 [internal] load build definition from Dockerfile.arm64",
      "attributes": {
        "col": "30",
        "filename": "sdk/0.3.0/host.star",
        "line": "45",
        "thread": "build"
      },
      "stream": 0
    },
    {
      "timestamp": "2025-10-01T13:35:52.436725-04:00",
      "message": "#1 transferring dockerfile: 1.85kB done",
      "attributes": {
        "col": "30",
        "filename": "sdk/0.3.0/host.star",
        "line": "45",
        "thread": "build"
      },
      "stream": 0
    },
    {
      "timestamp": "2025-10-01T13:35:52.438401-04:00",
      "message": "#1 DONE 0.0s",
      "attributes": {
        "col": "30",
        "filename": "sdk/0.3.0/host.star",
        "line": "45",
        "thread": "build"
      },
      "stream": 0
    },
    {
      "timestamp": "2025-10-01T13:35:52.440071-04:00",
      "message": "#2 [internal] load metadata for docker.io/library/ubuntu:latest",
      "attributes": {
        "col": "30",
        "filename": "sdk/0.3.0/host.star",
        "line": "45",
        "thread": "build"
      },
      "stream": 0
    },
    {
      "timestamp": "2025-10-01T13:35:52.441482-04:00",
      "message": "#2 DONE 0.1s",
      "attributes": {
        "col": "30",
        "filename": "sdk/0.3.0/host.star",
        "line": "45",
        "thread": "build"
      },
      "stream": 0
    },
    {
      "timestamp": "2025-10-01T13:35:52.442761-04:00",
      "message": "",
      "attributes": {
        "col": "30",
        "filename": "sdk/0.3.0/host.star",
        "line": "45",
        "thread": "build"
      },
      "stream": 0
    },
    {
      "timestamp": "2025-10-01T13:35:52.444776-04:00",
      "message": "#3 [internal] load .dockerignore",
      "attributes": {
        "col": "30",
        "filename": "sdk/0.3.0/host.star",
        "line": "45",
        "thread": "build"
      },
      "stream": 0
    },
    {
      "timestamp": "2025-10-01T13:35:52.446036-04:00",
      "message": "#3 transferring context: 2B done",
      "attributes": {
        "col": "30",
        "filename": "sdk/0.3.0/host.star",
        "line": "45",
        "thread": "build"
      },
      "stream": 0
    },
    {
      "timestamp": "2025-10-01T13:35:52.44742-04:00",
      "message": "#3 DONE 0.0s",
      "attributes": {
        "col": "30",
        "filename": "sdk/0.3.0/host.star",
        "line": "45",
        "thread": "build"
      },
      "stream": 0
    },
    {
      "timestamp": "2025-10-01T13:35:52.448721-04:00",
      "message": "",
      "attributes": {
        "col": "30",
        "filename": "sdk/0.3.0/host.star",
        "line": "45",
        "thread": "build"
      },
      "stream": 0
    },
    {
      "timestamp": "2025-10-01T13:35:52.45012-04:00",
      "message": "#4 [internal] load build context",
      "attributes": {
        "col": "30",
        "filename": "sdk/0.3.0/host.star",
        "line": "45",
        "thread": "build"
      },
      "stream": 0
    },
    {
      "timestamp": "2025-10-01T13:35:52.451508-04:00",
      "message": "#4 DONE 0.0s",
      "attributes": {
        "col": "30",
        "filename": "sdk/0.3.0/host.star",
        "line": "45",
        "thread": "build"
      },
      "stream": 0
    },
    {
      "timestamp": "2025-10-01T13:35:52.453362-04:00",
      "message": "",
      "attributes": {
        "col": "30",
        "filename": "sdk/0.3.0/host.star",
        "line": "45",
        "thread": "build"
      },
      "stream": 0
    },
    {
      "timestamp": "2025-10-01T13:35:52.45487-04:00",
      "message": "#5 [1/7] FROM docker.io/library/ubuntu:latest@sha256:353675e2a41babd526e2b837d7ec780c2a05bca0164f7ea5dbbd433d21d166fc",
      "attributes": {
        "col": "30",
        "filename": "sdk/0.3.0/host.star",
        "line": "45",
        "thread": "build"
      },
      "stream": 0
    },
    {
      "timestamp": "2025-10-01T13:35:52.456241-04:00",
      "message": "#5 resolve docker.io/library/ubuntu:latest@sha256:353675e2a41babd526e2b837d7ec780c2a05bca0164f7ea5dbbd433d21d166fc 0.0s done",
      "attributes": {
        "col": "30",
        "filename": "sdk/0.3.0/host.star",
        "line": "45",
        "thread": "build"
      },
      "stream": 0
    },
    {
      "timestamp": "2025-10-01T13:35:52.457711-04:00",
      "message": "#5 DONE 0.0s",
      "attributes": {
        "col": "30",
        "filename": "sdk/0.3.0/host.star",
        "line": "45",
        "thread": "build"
      },
      "stream": 0
    },
    {
      "timestamp": "2025-10-01T13:35:52.540439-04:00",
      "message": "",
      "attributes": {
        "col": "30",
        "filename": "sdk/0.3.0/host.star",
        "line": "45",
        "thread": "build"
      },
      "stream": 0
    },
    {
      "timestamp": "2025-10-01T13:35:52.540582-04:00",
      "message": "#5 [1/7] FROM docker.io/library/ubuntu:latest@sha256:353675e2a41babd526e2b837d7ec780c2a05bca0164f7ea5dbbd433d21d166fc",
      "attributes": {
        "col": "30",
        "filename": "sdk/0.3.0/host.star",
        "line": "45",
        "thread": "build"
      },
      "stream": 0
    },
    {
      "timestamp": "2025-10-01T13:35:52.542779-04:00",
      "message": "#5 DONE 0.0s",
      "attributes": {
        "col": "30",
        "filename": "sdk/0.3.0/host.star",
        "line": "45",
        "thread": "build"
      },
      "stream": 0
    },
    {
      "timestamp": "2025-10-01T13:35:52.54404-04:00",
      "message": "",
      "attributes": {
        "col": "30",
        "filename": "sdk/0.3.0/host.star",
        "line": "45",
        "thread": "build"
      },
      "stream": 0
    },
    {
      "timestamp": "2025-10-01T13:35:52.545709-04:00",
      "message": "#6 [2/7] RUN apt-get update \u0026\u0026 apt-get install -y     curl     wget     file     \u0026\u0026 rm -rf /var/lib/apt/lists/*",
      "attributes": {
        "col": "30",
        "filename": "sdk/0.3.0/host.star",
        "line": "45",
        "thread": "build"
      },
      "stream": 0
    },
    {
      "timestamp": "2025-10-01T13:35:52.547193-04:00",
      "message": "#6 CACHED",
      "attributes": {
        "col": "30",
        "filename": "sdk/0.3.0/host.star",
        "line": "45",
        "thread": "build"
      },
      "stream": 0
    },
    {
      "timestamp": "2025-10-01T13:35:52.548554-04:00",
      "message": "",
      "attributes": {
        "col": "30",
        "filename": "sdk/0.3.0/host.star",
        "line": "45",
        "thread": "build"
      },
      "stream": 0
    },
    {
      "timestamp": "2025-10-01T13:35:52.54991-04:00",
      "message": "#4 [internal] load build context",
      "attributes": {
        "col": "30",
        "filename": "sdk/0.3.0/host.star",
        "line": "45",
        "thread": "build"
      },
      "stream": 0
    },
    {
      "timestamp": "2025-10-01T13:35:52.691569-04:00",
      "message": "#4 transferring context: 12.86MB 0.2s done",
      "attributes": {
        "col": "30",
        "filename": "sdk/0.3.0/host.star",
        "line": "45",
        "thread": "build"
      },
      "stream": 0
    },
    {
      "timestamp": "2025-10-01T13:35:52.691697-04:00",
      "message": "#4 DONE 0.2s",
      "attributes": {
        "col": "30",
        "filename": "sdk/0.3.0/host.star",
        "line": "45",
        "thread": "build"
      },
      "stream": 0
    },
    {
      "timestamp": "2025-10-01T13:35:52.693224-04:00",
      "message": "",
      "attributes": {
        "col": "30",
        "filename": "sdk/0.3.0/host.star",
        "line": "45",
        "thread": "build"
      },
      "stream": 0
    },
    {
      "timestamp": "2025-10-01T13:35:52.694489-04:00",
      "message": "#7 [3/7] COPY .build/packages/ocuroot_0.3.16_arm64.deb /tmp/ocuroot.deb",
      "attributes": {
        "col": "30",
        "filename": "sdk/0.3.0/host.star",
        "line": "45",
        "thread": "build"
      },
      "stream": 0
    },
    {
      "timestamp": "2025-10-01T13:35:52.695701-04:00",
      "message": "#7 DONE 0.0s",
      "attributes": {
        "col": "30",
        "filename": "sdk/0.3.0/host.star",
        "line": "45",
        "thread": "build"
      },
      "stream": 0
    },
    {
      "timestamp": "2025-10-01T13:35:52.698584-04:00",
      "message": "",
      "attributes": {
        "col": "30",
        "filename": "sdk/0.3.0/host.star",
        "line": "45",
        "thread": "build"
      },
      "stream": 0
    },
    {
      "timestamp": "2025-10-01T13:35:52.699679-04:00",
      "message": "#8 [4/7] RUN dpkg -i /tmp/ocuroot.deb || (apt-get update \u0026\u0026 apt-get install -f -y \u0026\u0026 dpkg -i /tmp/ocuroot.deb)",
      "attributes": {
        "col": "30",
        "filename": "sdk/0.3.0/host.star",
        "line": "45",
        "thread": "build"
      },
      "stream": 0
    },
    {
      "timestamp": "2025-10-01T13:35:52.842689-04:00",
      "message": "#8 0.101 Selecting previously unselected package ocuroot.",
      "attributes": {
        "col": "30",
        "filename": "sdk/0.3.0/host.star",
        "line": "45",
        "thread": "build"
      },
      "stream": 0
    },
    {
      "timestamp": "2025-10-01T13:35:52.842796-04:00",
      "message": "#8 0.105 (Reading database ... 5052 files and directories currently installed.)",
      "attributes": {
        "col": "30",
        "filename": "sdk/0.3.0/host.star",
        "line": "45",
        "thread": "build"
      },
      "stream": 0
    },
    {
      "timestamp": "2025-10-01T13:35:52.844179-04:00",
      "message": "#8 0.105 Preparing to unpack /tmp/ocuroot.deb ...",
      "attributes": {
        "col": "30",
        "filename": "sdk/0.3.0/host.star",
        "line": "45",
        "thread": "build"
      },
      "stream": 0
    },
    {
      "timestamp": "2025-10-01T13:35:52.845897-04:00",
      "message": "#8 0.109 Unpacking ocuroot (0.3.16) ...",
      "attributes": {
        "col": "30",
        "filename": "sdk/0.3.0/host.star",
        "line": "45",
        "thread": "build"
      },
      "stream": 0
    },
    {
      "timestamp": "2025-10-01T13:35:52.993855-04:00",
      "message": "#8 0.215 Setting up ocuroot (0.3.16) ...",
      "attributes": {
        "col": "30",
        "filename": "sdk/0.3.0/host.star",
        "line": "45",
        "thread": "build"
      },
      "stream": 0
    },
    {
      "timestamp": "2025-10-01T13:35:52.99414-04:00",
      "message": "#8 DONE 0.3s",
      "attributes": {
        "col": "30",
        "filename": "sdk/0.3.0/host.star",
        "line": "45",
        "thread": "build"
      },
      "stream": 0
    },
    {
      "timestamp": "2025-10-01T13:35:52.997758-04:00",
      "message": "",
      "attributes": {
        "col": "30",
        "filename": "sdk/0.3.0/host.star",
        "line": "45",
        "thread": "build"
      },
      "stream": 0
    },
    {
      "timestamp": "2025-10-01T13:35:52.999496-04:00",
      "message": "#9 [5/7] RUN set -e \u0026\u0026     echo \"=== Package Installation Tests ===\" \u0026\u0026     dpkg -l | grep ocuroot \u0026\u0026     echo \"✓ Package is installed\" \u0026\u0026         echo \"=== Binary Tests ===\" \u0026\u0026     ls -la /usr/bin/ocuroot \u0026\u0026     file /usr/bin/ocuroot \u0026\u0026     echo \"✓ Binary exists and is executable\" \u0026\u0026         echo \"=== Architecture Tests ===\" \u0026\u0026     file /usr/bin/ocuroot | grep \"aarch64\" \u0026\u0026     echo \"✓ Binary is correct architecture (aarch64)\" \u0026\u0026         echo \"=== Functionality Tests ===\" \u0026\u0026     ocuroot --help \u003e /dev/null \u0026\u0026     echo \"✓ Help command works\" \u0026\u0026     ocuroot version \u003e /dev/null \u0026\u0026     echo \"✓ Version command works\" \u0026\u0026         echo \"=== Package Metadata Tests ===\" \u0026\u0026     PACKAGE_VERSION=$(dpkg -s ocuroot | grep '^Version:' | cut -d' ' -f2) \u0026\u0026     echo \"Package version: $PACKAGE_VERSION\" \u0026\u0026     EXPECTED_PACKAGE_VERSION=$(echo \"0.3.16\" | cut -d'-' -f1) \u0026\u0026     echo \"Expected package version: $EXPECTED_PACKAGE_VERSION\" \u0026\u0026     [ \"$PACKAGE_VERSION\" = \"$EXPECTED_PACKAGE_VERSION\" ] \u0026\u0026     echo \"✓ Package version matches expected version\" \u0026\u0026         echo \"=== All tests passed! ===\"",
      "attributes": {
        "col": "30",
        "filename": "sdk/0.3.0/host.star",
        "line": "45",
        "thread": "build"
      },
      "stream": 0
    },
    {
      "timestamp": "2025-10-01T13:35:53.144903-04:00",
      "message": "#9 0.113 === Package Installation Tests ===",
      "attributes": {
        "col": "30",
        "filename": "sdk/0.3.0/host.star",
        "line": "45",
        "thread": "build"
      },
      "stream": 0
    },
    {
      "timestamp": "2025-10-01T13:35:53.145035-04:00",
      "message": "#9 0.116 ii  ocuroot                   0.3.16                            arm64        Ocuroot is the Ocuroot CLI tool.",
      "attributes": {
        "col": "30",
        "filename": "sdk/0.3.0/host.star",
        "line": "45",
        "thread": "build"
      },
      "stream": 0
    },
    {
      "timestamp": "2025-10-01T13:35:53.149512-04:00",
      "message": "#9 0.116 ✓ Package is installed",
      "attributes": {
        "col": "30",
        "filename": "sdk/0.3.0/host.star",
        "line": "45",
        "thread": "build"
      },
      "stream": 0
    },
    {
      "timestamp": "2025-10-01T13:35:53.150695-04:00",
      "message": "#9 0.116 === Binary Tests ===",
      "attributes": {
        "col": "30",
        "filename": "sdk/0.3.0/host.star",
        "line": "45",
        "thread": "build"
      },
      "stream": 0
    },
    {
      "timestamp": "2025-10-01T13:35:53.151885-04:00",
      "message": "#9 0.117 -rwxr-xr-x 1 root root 25935053 Oct  1 17:35 /usr/bin/ocuroot",
      "attributes": {
        "col": "30",
        "filename": "sdk/0.3.0/host.star",
        "line": "45",
        "thread": "build"
      },
      "stream": 0
    },
    {
      "timestamp": "2025-10-01T13:35:53.153698-04:00",
      "message": "#9 0.123 /usr/bin/ocuroot: ELF 64-bit LSB executable, ARM aarch64, version 1 (SYSV), statically linked, BuildID[sha1]=5356e2608e269a6e8913e77e406c2a5dca120c30, with debug_info, not stripped",
      "attributes": {
        "col": "30",
        "filename": "sdk/0.3.0/host.star",
        "line": "45",
        "thread": "build"
      },
      "stream": 0
    },
    {
      "timestamp": "2025-10-01T13:35:53.155151-04:00",
      "message": "#9 0.123 ✓ Binary exists and is executable",
      "attributes": {
        "col": "30",
        "filename": "sdk/0.3.0/host.star",
        "line": "45",
        "thread": "build"
      },
      "stream": 0
    },
    {
      "timestamp": "2025-10-01T13:35:53.15634-04:00",
      "message": "#9 0.123 === Architecture Tests ===",
      "attributes": {
        "col": "30",
        "filename": "sdk/0.3.0/host.star",
        "line": "45",
        "thread": "build"
      },
      "stream": 0
    },
    {
      "timestamp": "2025-10-01T13:35:53.157635-04:00",
      "message": "#9 0.129 /usr/bin/ocuroot: ELF 64-bit LSB executable, ARM aarch64, version 1 (SYSV), statically linked, BuildID[sha1]=5356e2608e269a6e8913e77e406c2a5dca120c30, with debug_info, not stripped",
      "attributes": {
        "col": "30",
        "filename": "sdk/0.3.0/host.star",
        "line": "45",
        "thread": "build"
      },
      "stream": 0
    },
    {
      "timestamp": "2025-10-01T13:35:53.158888-04:00",
      "message": "#9 0.129 ✓ Binary is correct architecture (aarch64)",
      "attributes": {
        "col": "30",
        "filename": "sdk/0.3.0/host.star",
        "line": "45",
        "thread": "build"
      },
      "stream": 0
    },
    {
      "timestamp": "2025-10-01T13:35:53.160132-04:00",
      "message": "#9 0.129 === Functionality Tests ===",
      "attributes": {
        "col": "30",
        "filename": "sdk/0.3.0/host.star",
        "line": "45",
        "thread": "build"
      },
      "stream": 0
    },
    {
      "timestamp": "2025-10-01T13:35:53.161667-04:00",
      "message": "#9 0.136 ✓ Help command works",
      "attributes": {
        "col": "30",
        "filename": "sdk/0.3.0/host.star",
        "line": "45",
        "thread": "build"
      },
      "stream": 0
    },
    {
      "timestamp": "2025-10-01T13:35:53.162846-04:00",
      "message": "#9 0.139 Logs at: /root/.ocuroot/logs/1759340153062099139-version.log",
      "attributes": {
        "col": "30",
        "filename": "sdk/0.3.0/host.star",
        "line": "45",
        "thread": "build"
      },
      "stream": 0
    },
    {
      "timestamp": "2025-10-01T13:35:53.164106-04:00",
      "message": "#9 0.139 ✓ Version command works",
      "attributes": {
        "col": "30",
        "filename": "sdk/0.3.0/host.star",
        "line": "45",
        "thread": "build"
      },
      "stream": 0
    },
    {
      "timestamp": "2025-10-01T13:35:53.165376-04:00",
      "message": "#9 0.139 === Package Metadata Tests ===",
      "attributes": {
        "col": "30",
        "filename": "sdk/0.3.0/host.star",
        "line": "45",
        "thread": "build"
      },
      "stream": 0
    },
    {
      "timestamp": "2025-10-01T13:35:53.166571-04:00",
      "message": "#9 0.142 Package version: 0.3.16",
      "attributes": {
        "col": "30",
        "filename": "sdk/0.3.0/host.star",
        "line": "45",
        "thread": "build"
      },
      "stream": 0
    },
    {
      "timestamp": "2025-10-01T13:35:53.168094-04:00",
      "message": "#9 0.143 Expected package version: 0.3.16",
      "attributes": {
        "col": "30",
        "filename": "sdk/0.3.0/host.star",
        "line": "45",
        "thread": "build"
      },
      "stream": 0
    },
    {
      "timestamp": "2025-10-01T13:35:53.170299-04:00",
      "message": "#9 0.143 ✓ Package version matches expected version",
      "attributes": {
        "col": "30",
        "filename": "sdk/0.3.0/host.star",
        "line": "45",
        "thread": "build"
      },
      "stream": 0
    },
    {
      "timestamp": "2025-10-01T13:35:53.171726-04:00",
      "message": "#9 0.143 === All tests passed! ===",
      "attributes": {
        "col": "30",
        "filename": "sdk/0.3.0/host.star",
        "line": "45",
        "thread": "build"
      },
      "stream": 0
    },
    {
      "timestamp": "2025-10-01T13:35:53.173034-04:00",
      "message": "#9 DONE 0.2s",
      "attributes": {
        "col": "30",
        "filename": "sdk/0.3.0/host.star",
        "line": "45",
        "thread": "build"
      },
      "stream": 0
    },
    {
      "timestamp": "2025-10-01T13:35:53.174269-04:00",
      "message": "",
      "attributes": {
        "col": "30",
        "filename": "sdk/0.3.0/host.star",
        "line": "45",
        "thread": "build"
      },
      "stream": 0
    },
    {
      "timestamp": "2025-10-01T13:35:53.175674-04:00",
      "message": "#10 [6/7] RUN rm /tmp/ocuroot.deb",
      "attributes": {
        "col": "30",
        "filename": "sdk/0.3.0/host.star",
        "line": "45",
        "thread": "build"
      },
      "stream": 0
    },
    {
      "timestamp": "2025-10-01T13:35:53.296026-04:00",
      "message": "#10 DONE 0.1s",
      "attributes": {
        "col": "30",
        "filename": "sdk/0.3.0/host.star",
        "line": "45",
        "thread": "build"
      },
      "stream": 0
    },
    {
      "timestamp": "2025-10-01T13:35:53.296158-04:00",
      "message": "",
      "attributes": {
        "col": "30",
        "filename": "sdk/0.3.0/host.star",
        "line": "45",
        "thread": "build"
      },
      "stream": 0
    },
    {
      "timestamp": "2025-10-01T13:35:53.756299-04:00",
      "message": "#11 [7/7] WORKDIR /root",
      "attributes": {
        "col": "30",
        "filename": "sdk/0.3.0/host.star",
        "line": "45",
        "thread": "build"
      },
      "stream": 0
    },
    {
      "timestamp": "2025-10-01T13:35:53.758912-04:00",
      "message": "#11 DONE 0.0s",
      "attributes": {
        "col": "30",
        "filename": "sdk/0.3.0/host.star",
        "line": "45",
        "thread": "build"
      },
      "stream": 0
    },
    {
      "timestamp": "2025-10-01T13:35:53.760612-04:00",
      "message": "",
      "attributes": {
        "col": "30",
        "filename": "sdk/0.3.0/host.star",
        "line": "45",
        "thread": "build"
      },
      "stream": 0
    },
    {
      "timestamp": "2025-10-01T13:35:53.7617-04:00",
      "message": "#12 exporting to image",
      "attributes": {
        "col": "30",
        "filename": "sdk/0.3.0/host.star",
        "line": "45",
        "thread": "build"
      },
      "stream": 0
    },
    {
      "timestamp": "2025-10-01T13:35:53.762811-04:00",
      "message": "#12 exporting layers",
      "attributes": {
        "col": "30",
        "filename": "sdk/0.3.0/host.star",
        "line": "45",
        "thread": "build"
      },
      "stream": 0
    },
    {
      "timestamp": "2025-10-01T13:35:54.049131-04:00",
      "message": "#12 exporting layers 0.8s done",
      "attributes": {
        "col": "30",
        "filename": "sdk/0.3.0/host.star",
        "line": "45",
        "thread": "build"
      },
      "stream": 0
    },
    {
      "timestamp": "2025-10-01T13:35:54.049491-04:00",
      "message": "#12 exporting manifest sha256:7c7de53674ec9ae33b17984fb6ae3a4b0818d2d25115067c314ae52241244cc2 done",
      "attributes": {
        "col": "30",
        "filename": "sdk/0.3.0/host.star",
        "line": "45",
        "thread": "build"
      },
      "stream": 0
    },
    {
      "timestamp": "2025-10-01T13:35:54.055421-04:00",
      "message": "#12 exporting config sha256:127d462a1a1278662c2c91d678fc73a2fd7201d42508de3b968904548f71d770 done",
      "attributes": {
        "col": "30",
        "filename": "sdk/0.3.0/host.star",
        "line": "45",
        "thread": "build"
      },
      "stream": 0
    },
    {
      "timestamp": "2025-10-01T13:35:54.056782-04:00",
      "message": "#12 naming to docker.io/library/ocuroot-test-arm64:latest done",
      "attributes": {
        "col": "30",
        "filename": "sdk/0.3.0/host.star",
        "line": "45",
        "thread": "build"
      },
      "stream": 0
    },
    {
      "timestamp": "2025-10-01T13:35:54.058143-04:00",
      "message": "#12 unpacking to docker.io/library/ocuroot-test-arm64:latest",
      "attributes": {
        "col": "30",
        "filename": "sdk/0.3.0/host.star",
        "line": "45",
        "thread": "build"
      },
      "stream": 0
    },
    {
      "timestamp": "2025-10-01T13:35:54.173219-04:00",
      "message": "#12 unpacking to docker.io/library/ocuroot-test-arm64:latest 0.2s done",
      "attributes": {
        "col": "30",
        "filename": "sdk/0.3.0/host.star",
        "line": "45",
        "thread": "build"
      },
      "stream": 0
    },
    {
      "timestamp": "2025-10-01T13:35:54.211212-04:00",
      "message": "#12 DONE 1.0s",
      "attributes": {
        "col": "30",
        "filename": "sdk/0.3.0/host.star",
        "line": "45",
        "thread": "build"
      },
      "stream": 0
    },
    {
      "timestamp": "2025-10-01T13:35:54.213373-04:00",
      "message": "✓ arm64 package test passed",
      "attributes": {
        "col": "30",
        "filename": "sdk/0.3.0/host.star",
        "line": "45",
        "thread": "build"
      },
      "stream": 0
    },
    {
      "timestamp": "2025-10-01T13:35:54.21349-04:00",
      "message": "🎉 arm64 package test passed!",
      "attributes": {
        "col": "30",
        "filename": "sdk/0.3.0/host.star",
        "line": "45",
        "thread": "build"
      },
      "stream": 0
    },
    {
      "timestamp": "2025-10-01T13:35:54.21502-04:00",
      "message": "",
      "attributes": {
        "col": "30",
        "filename": "sdk/0.3.0/host.star",
        "line": "45",
        "thread": "build"
      },
      "stream": 0
    },
    {
      "timestamp": "2025-10-01T13:35:54.216291-04:00",
      "message": "Available test image:",
      "attributes": {
        "col": "30",
        "filename": "sdk/0.3.0/host.star",
        "line": "45",
        "thread": "build"
      },
      "stream": 0
    },
    {
      "timestamp": "2025-10-01T13:35:54.218193-04:00",
      "message": "  - ocuroot-test-arm64 (for arm64 testing)",
      "attributes": {
        "col": "30",
        "filename": "sdk/0.3.0/host.star",
        "line": "45",
        "thread": "build"
      },
      "stream": 0
    },
    {
      "timestamp": "2025-10-01T13:35:54.219357-04:00",
      "message": "",
      "attributes": {
        "col": "30",
        "filename": "sdk/0.3.0/host.star",
        "line": "45",
        "thread": "build"
      },
      "stream": 0
    },
    {
      "timestamp": "2025-10-01T13:35:54.22052-04:00",
      "message": "To run interactive test:",
      "attributes": {
        "col": "30",
        "filename": "sdk/0.3.0/host.star",
        "line": "45",
        "thread": "build"
      },
      "stream": 0
    },
    {
      "timestamp": "2025-10-01T13:35:54.221737-04:00",
      "message": "  docker run -it --rm ocuroot-test-arm64",
      "attributes": {
        "col": "30",
        "filename": "sdk/0.3.0/host.star",
        "line": "45",
        "thread": "build"
      },
      "stream": 0
    },
    {
      "timestamp": "2025-10-01T13:35:56.65132-04:00",
      "message": "a ocuroot",
      "attributes": {
        "col": "30",
        "filename": "sdk/0.3.0/host.star",
        "line": "45",
        "thread": "build"
      },
      "stream": 0
    },
    {
      "timestamp": "2025-10-01T13:35:57.427695-04:00",
      "message": "",
      "attributes": {
        "col": "30",
        "filename": "sdk/0.3.0/host.star",
        "line": "45",
        "thread": "build"
      },
      "stream": 0
    }
  ]
}